nista_learn/__init__.py
nista_learn/regressions.py
nista_learn/regressions_functions.py
nista_learn-0.0.2.dist-info/LICENCE
nista_learn-0.0.2.dist-info/METADATA
nista_learn-0.0.2.dist-info/WHEEL
nista_learn-0.0.2.dist-info/top_level.txt
nista_learn-0.0.2.dist-info/RECORD
