Metadata-Version: 2.1
Name: nista-learn
Version: 0.0.2
Summary: A small machine learning package
Home-page: https://github.com/wariored/nista_learn
Author: Cheikh Tidjane Konteye
Author-email: cheikh@cheikhkonteye.com
License: UNKNOWN
Platform: UNKNOWN
Classifier: Programming Language :: Python :: 3.6
Classifier: License :: OSI Approved :: MIT License
Classifier: Operating System :: OS Independent
